CHANGES.txt
LICENSE.txt
README.txt
setup.py
django_coretext.egg-info/PKG-INFO
django_coretext.egg-info/SOURCES.txt
django_coretext.egg-info/dependency_links.txt
django_coretext.egg-info/requires.txt
django_coretext.egg-info/top_level.txt
text/__init__.py
text/core/__init__.py
text/core/admin.py
text/core/models.py
text/core/views.py
text/templates/default.html
text/templates/parts/dom-datalist.html
text/templates/parts/dom-image.html
text/templates/parts/dom-list.html
text/templates/parts/dom-relativelink.html